eyelab/__init__.py
eyelab/commands/__init__.py
eyelab/commands/layeritem.py
eyelab/commands/thin_out.py
eyelab/config.py
eyelab/dialogs/__init__.py
eyelab/dialogs/addannotation.py
eyelab/dialogs/help/__init__.py
eyelab/dialogs/help/areaannotation_help.py
eyelab/dialogs/help/help_dialog.py
eyelab/dialogs/help/introduction_help.py
eyelab/dialogs/help/layerannotation_help.py
eyelab/dialogs/help/shortcut_help.py
eyelab/main.py
eyelab/models/__init__.py
eyelab/models/layereditor.py
eyelab/models/scene.py
eyelab/models/treeitemdelegate.py
eyelab/models/treeview/__init__.py
eyelab/models/treeview/areaitem.py
eyelab/models/treeview/itemgroup.py
eyelab/models/treeview/itemmodel.py
eyelab/models/treeview/layeritem.py
eyelab/models/utils.py
eyelab/models/viewtab.py
eyelab/tools/__init__.py
eyelab/tools/fillsame.py
eyelab/tools/inspection.py
eyelab/tools/pen.py
eyelab/tools/splinetool.py
eyelab/tools/template.py
eyelab/views/__init__.py
eyelab/views/compile_resource.sh
eyelab/views/compile_views.sh
eyelab/views/data_view.py
eyelab/views/enface_view.py
eyelab/views/graphicsview.py
eyelab/views/ui/__init__.py
eyelab/views/ui/cursors/__init__.py
eyelab/views/ui/cursors/inspection_cursor.jpeg
eyelab/views/ui/cursors/inspection_cursor_vertical.jpeg
eyelab/views/ui/cursors/navigation_cursor.svg
eyelab/views/ui/cursors/path_cursor.svg
eyelab/views/ui/cursors/pen_cursor.svg
eyelab/views/ui/icons/__init__.py
eyelab/views/ui/icons/baseline-add_circle-24px.svg
eyelab/views/ui/icons/baseline-arrow_downward-24px.svg
eyelab/views/ui/icons/baseline-arrow_upward-24px.svg
eyelab/views/ui/icons/baseline-delete-24px.svg
eyelab/views/ui/icons/baseline-edit-24px.svg
eyelab/views/ui/icons/baseline-filter-none-24px.svg
eyelab/views/ui/icons/baseline-navigate-before-24px.svg
eyelab/views/ui/icons/baseline-navigate-next-24px.svg
eyelab/views/ui/icons/baseline-redo-24px.svg
eyelab/views/ui/icons/baseline-save-24px.svg
eyelab/views/ui/icons/baseline-settings-20px.svg
eyelab-0.4.1.dist-info/LICENSE
eyelab-0.4.1.dist-info/WHEEL
eyelab-0.4.1.dist-info/METADATA
eyelab-0.4.1.dist-info/RECORD
