Metadata-Version: 2.1
Name: eyelab
Version: 0.4.1
Summary: Multi-modal annotation tool for eye imaging data
License: MIT
Author: Olivier Morelle
Author-email: oli4morelle@gmail.com
Requires-Python: >=3.8,<3.10
Classifier: License :: OSI Approved :: MIT License
Classifier: Programming Language :: Python :: 3
Classifier: Programming Language :: Python :: 3.8
Classifier: Programming Language :: Python :: 3.9
Requires-Dist: PySide6 (==6.1.3)
Requires-Dist: eyepie (>=0.6.7,<0.7.0)
Requires-Dist: numpy (>=1.22)
Requires-Dist: qimage2ndarray (==1.9.0)
Requires-Dist: requests (>=2.27.1,<3.0.0)
Requires-Dist: scikit-image (>=0.19.1,<0.20.0)
